bayesNetworks18051/__init__.py
bayesNetworks18051/bayesNetworks18051.py
bayesNetworks18051/redes.py
bayesNetworks18051-0.0.2.dist-info/METADATA
bayesNetworks18051-0.0.2.dist-info/WHEEL
bayesNetworks18051-0.0.2.dist-info/top_level.txt
bayesNetworks18051-0.0.2.dist-info/RECORD
